drm_free_audible/__init__.py
drm_free_audible/drm.py
drm_free_audible/logging_config.yaml
drm_free_audible/main.py
drm_free_audible-0.1.7.dist-info/LICENSE
drm_free_audible-0.1.7.dist-info/METADATA
drm_free_audible-0.1.7.dist-info/WHEEL
drm_free_audible-0.1.7.dist-info/entry_points.txt
drm_free_audible-0.1.7.dist-info/RECORD
